<?xml version="1.0" encoding="UTF-8"?>
<prompt xmlns:xsi="http://www.w3.org/2001/XMLSchema-instance"
      xsi:noNamespaceSchemaLocation="https://jabrena.github.io/pml/schemas/0.8.0/pml.xsd"
      id="315-frameworks-spring-mongodb">
  <metadata>
    <author>Juan Antonio Breña Moral</author>
    <version>0.17.0</version>
    <license>Apache-2.0</license>
    <description>Use when you need to design or implement MongoDB data access in Spring Boot — including document modeling, Spring Data Mongo repositories/templates, indexing, optimistic concurrency, and error handling. This should trigger for requests such as Add MongoDB in Spring Boot; Review Spring Data Mongo design; Improve error handling for Mongo writes; Model MongoDB documents for a Spring Boot service; Configure Spring Data MongoDB indexes or transactions.</description>
  </metadata>

  <title>Spring Boot — MongoDB</title>
  <goal><![CDATA[
Apply Spring Data MongoDB guidance with concrete examples for design, implementation, and error handling.
]]></goal>

  <constraints>
    <constraints-description>Compile before MongoDB refactors; verify after changes.</constraints-description>
    <constraint-list>
      <constraint>**MANDATORY**: Run `./mvnw compile` or `mvn compile` before applying any change</constraint>
      <constraint>**SAFETY**: If compilation fails, stop immediately</constraint>
      <constraint>**VERIFY**: Run `./mvnw clean verify` or `mvn clean verify` after applying improvements</constraint>
      <constraint>**BEFORE APPLYING**: Read the reference for detailed rules and examples</constraint>
    </constraint-list>
  </constraints>

  <triggers>
    <trigger-list>
        <trigger>Add MongoDB in Spring Boot</trigger>
        <trigger>Review Spring Data Mongo repositories/documents</trigger>
        <trigger>Improve duplicate key handling, retries, or optimistic locking in Mongo flows</trigger>
        <trigger>Model MongoDB documents for a Spring Boot service</trigger>
        <trigger>Configure Spring Data MongoDB indexes or transactions</trigger>
    </trigger-list>
  </triggers>

  <steps>
    <step number="1"><step-title>Read reference and assess project context</step-title><step-content>Read `references/315-frameworks-spring-mongodb.md` and inspect persistence setup before proposing changes.</step-content></step>
    <step number="2"><step-title>Gather scope and decide target improvements</step-title><step-content>Identify data model, consistency, and query requirements to define safe improvements.</step-content></step>
    <step number="3"><step-title>Apply framework-aligned changes</step-title><step-content>Implement/refactor mappings, repositories, indexes, and failure handling policies.</step-content></step>
    <step number="4"><step-title>Run verification and report results</step-title><step-content>Execute build/tests and summarize what changed, what was verified, and follow-up actions.</step-content></step>
  </steps>
</prompt>
