<?xml version="1.0" encoding="UTF-8"?>
<prompt xmlns:xsi="http://www.w3.org/2001/XMLSchema-instance"
      xsi:noNamespaceSchemaLocation="https://jabrena.github.io/pml/schemas/0.7.0/pml.xsd"
      id="415-frameworks-quarkus-mongodb">
  <metadata>
    <author>Juan Antonio Breña Moral</author>
    <version>0.17.0-SNAPSHOT</version>
    <license>Apache-2.0</license>
    <description>Use when you need MongoDB persistence in Quarkus — including Panache Mongo entities/repositories, document design, indexes, transactions where applicable, and error handling. This should trigger for requests such as Add MongoDB in Quarkus; Review Quarkus Mongo Panache design; Improve Mongo error handling in Quarkus services; Model MongoDB documents for a Quarkus service; Configure Quarkus MongoDB clients codecs or transactions.</description>
  </metadata>

  <title>Quarkus — MongoDB</title>
  <goal><![CDATA[
Apply Quarkus MongoDB guidance with concrete examples for design, implementation, and error handling.
]]></goal>

  <constraints>
    <constraints-description>Compile before MongoDB refactors; verify after changes.</constraints-description>
    <constraint-list>
      <constraint>**MANDATORY**: Run `./mvnw compile` or `mvn compile` before applying any change</constraint>
      <constraint>**SAFETY**: If compilation fails, stop immediately</constraint>
      <constraint>**VERIFY**: Run `./mvnw clean verify` or `mvn clean verify` after applying improvements</constraint>
      <constraint>**BEFORE APPLYING**: Read the reference for detailed rules and examples</constraint>
    </constraint-list>
  </constraints>

  <triggers>
    <trigger-list>
        <trigger>Add MongoDB in Quarkus</trigger>
        <trigger>Review Quarkus Mongo Panache entities/repositories</trigger>
        <trigger>Improve duplicate key handling, retry policy, or optimistic locking in Quarkus Mongo</trigger>
        <trigger>Model MongoDB documents for a Quarkus service</trigger>
        <trigger>Configure Quarkus MongoDB clients codecs or transactions</trigger>
    </trigger-list>
  </triggers>

  <steps>
    <step number="1"><step-title>Read reference and assess project context</step-title><step-content>Read `references/415-frameworks-quarkus-mongodb.md` and inspect persistence setup before proposing changes.</step-content></step>
    <step number="2"><step-title>Gather scope and decide target improvements</step-title><step-content>Identify model/query consistency needs and define safe improvements.</step-content></step>
    <step number="3"><step-title>Apply framework-aligned changes</step-title><step-content>Implement/refactor Panache Mongo mappings, repository access, and failure handling.</step-content></step>
    <step number="4"><step-title>Run verification and report results</step-title><step-content>Execute build/tests and summarize what changed, what was verified, and follow-up actions.</step-content></step>
  </steps>
</prompt>
