<?xml version="1.0" encoding="UTF-8"?>
<prompt xmlns:xsi="http://www.w3.org/2001/XMLSchema-instance"
      xsi:noNamespaceSchemaLocation="https://jabrena.github.io/pml/schemas/0.7.0/pml.xsd"
      id="133-java-testing-acceptance-tests">
  <metadata>
    <author>Juan Antonio Breña Moral</author>
    <version>0.13.0</version>
    <license>Apache-2.0</license>
    <description>Use when you need to implement acceptance tests from a Gherkin .feature file for framework-agnostic Java (no Spring Boot, Quarkus, Micronaut) — finding @acceptance scenarios, happy path with RestAssured, Testcontainers for DB/Kafka, WireMock for external REST. Requires .feature file in context.</description>
  </metadata>

  <title>Java acceptance tests from Gherkin</title>
  <goal><![CDATA[
Implement acceptance tests from Gherkin feature files. Given a .feature file in context, find @acceptance-tagged scenarios and implement happy-path tests with RestAssured, Testcontainers, and WireMock.

**What is covered in this Skill?**

- Parse Gherkin .feature files to find scenarios tagged @acceptance or @acceptance-tests
- Implement happy-path acceptance tests (one test per scenario)
- RestAssured for REST API testing (given/when/then, status codes, JSON body assertions)
- Testcontainers for databases (PostgreSQL, etc.) and Kafka
- WireMock for stubbing external REST APIs
- BaseAcceptanceTest base class with @BeforeAll coordinate propagation via System.setProperty
- Given-When-Then structure mapping Gherkin steps to setup, request, and assertions
- Maven dependencies: rest-assured, testcontainers, wiremock-standalone

**Preconditions:** (1) The Gherkin .feature file must be in context. (2) The project must NOT use Spring Boot, Quarkus, or Micronaut — for those frameworks, use @323-frameworks-spring-boot-testing-acceptance-tests or framework-specific rules.

**Scope:** Implements only happy-path scenarios. Use the reference for detailed examples and constraints.
]]></goal>

  <constraints>
    <constraints-description>Before applying any acceptance test changes, ensure the Gherkin .feature file is in context and the project compiles. If compilation fails or the feature file is missing, stop immediately.</constraints-description>
    <constraint-list>
      <constraint>**PRECONDITION**: The Gherkin .feature file MUST be in context; the project MUST NOT use Spring Boot, Quarkus, or Micronaut</constraint>
      <constraint>**MANDATORY**: Run `./mvnw compile` or `mvn compile` before applying any change</constraint>
      <constraint>**SAFETY**: If compilation fails, stop immediately and do not proceed</constraint>
      <constraint>**VERIFY**: Run `./mvnw clean verify` or `mvn clean verify` after applying improvements</constraint>
      <constraint>**BEFORE APPLYING**: Read the reference for detailed examples, good/bad patterns, and constraints</constraint>
    </constraint-list>
  </constraints>

  <triggers>
    <trigger-list>
        <trigger>Review Java code for acceptance tests</trigger>
        <trigger>Apply best practices for acceptance tests in Java code</trigger>
    </trigger-list>
  </triggers>

  <references>
    <reference-list>
        <reference>references/133-java-testing-acceptance-tests.md</reference>
    </reference-list>
  </references>
</prompt>
